<?xml version='1.0' encoding='utf-8'?>
<LHData>
  <CalendarDay>
    <DateISO>2025-08-31</DateISO>
    <DateDay>31</DateDay>
    <DateMonth>8</DateMonth>
    <DateYear>2025</DateYear>
    <DayOfYear>243</DayOfYear>
    <DayOfWeek Id="6">неділя</DayOfWeek>
    <Celebration>
      <Id>0</Id>
      <StringTitle>
        <span class="bold">
          <span class="uppercase">Св. Єроніма, пресвітера і Вчителя Церкви</span>
        </span>
      </StringTitle>
      <LiturgicalSeason>Звичайний період</LiturgicalSeason>
      <LiturgicalCelebrationLevel>3</LiturgicalCelebrationLevel>
      <LiturgicalCelebrationType>спомин</LiturgicalCelebrationType>
    </Celebration>
  </CalendarDay>
</LHData>